rojak/__init__.py
rojak/agents/__init__.py
rojak/agents/agent.py
rojak/agents/anthropic_agent.py
rojak/agents/openai_agent.py
rojak/client.py
rojak/mcp/__init__.py
rojak/mcp/mcp_client.py
rojak/retrievers/__init__.py
rojak/retrievers/qdrant_retriever.py
rojak/retrievers/retriever.py
rojak/types/__init__.py
rojak/types/types.py
rojak/utils/__init__.py
rojak/utils/helpers.py
rojak/workflows/__init__.py
rojak/workflows/agent_workflow.py
rojak/workflows/orchestrator_workflow.py
rojak-1.0.0.dist-info/LICENSE
rojak-1.0.0.dist-info/METADATA
rojak-1.0.0.dist-info/WHEEL
rojak-1.0.0.dist-info/RECORD
