Metadata-Version: 2.3
Name: rojak
Version: 1.0.0
Summary: Durable and scalable multi-agent orchestration framework.
Author: StreetLamb
Author-email: l.y.z.jerron@gmail.com
Requires-Python: >=3.12,<4.0
Classifier: Programming Language :: Python :: 3
Classifier: Programming Language :: Python :: 3.12
Classifier: Programming Language :: Python :: 3.13
Provides-Extra: anthropic
Provides-Extra: openai
Provides-Extra: qdrant-client
Requires-Dist: anthropic[bedrock] (>=0.42.0,<0.43.0) ; extra == "anthropic"
Requires-Dist: mcp (>=1.2.0,<2.0.0)
Requires-Dist: openai (>=1.55.3,<2.0.0) ; extra == "openai"
Requires-Dist: qdrant-client[fastembed] (>=1.12.1,<2.0.0) ; extra == "qdrant-client"
Requires-Dist: temporalio (>=1.8.0,<2.0.0)
